{
  "attacks": [
    {
      "id": "379_6195_1778786205000",
      "originId": "379",
      "targetId": "6195",
      "slowest": "catapult",
      "arrivalMs": 1778786205000,
      "catapultTarget": "14",
      "troops": {
        "spear": 0,
        "sword": 0,
        "axe": 0,
        "archer": 0,
        "spy": 1,
        "light": 0,
        "marcher": 0,
        "heavy": 0,
        "ram": 0,
        "catapult": 5,
        "knight": 0,
        "snob": 0,
        "militia": 0
      },
      "sent": true,
      "sentBy": "attack-bot-skip",
      "sentAt": 1778496252424
    },
    {
      "id": "379_12456_1778785888000",
      "originId": "379",
      "targetId": "12456",
      "slowest": "catapult",
      "arrivalMs": 1778785888000,
      "catapultTarget": "14",
      "troops": {
        "spear": 0,
        "sword": 0,
        "axe": 0,
        "archer": 0,
        "spy": 1,
        "light": 0,
        "marcher": 0,
        "heavy": 0,
        "ram": 0,
        "catapult": 5,
        "knight": 0,
        "snob": 0,
        "militia": 0
      },
      "sent": true,
      "sentBy": "attack-bot-skip",
      "sentAt": 1778496256418
    },
    {
      "id": "3790_6011_1778785351000",
      "originId": "3790",
      "targetId": "6011",
      "slowest": "catapult",
      "arrivalMs": 1778785351000,
      "catapultTarget": "14",
      "troops": {
        "spear": 0,
        "sword": 0,
        "axe": 0,
        "archer": 0,
        "spy": 1,
        "light": 0,
        "marcher": 0,
        "heavy": 0,
        "ram": 0,
        "catapult": 9,
        "knight": 0,
        "snob": 0,
        "militia": 0
      },
      "sent": true,
      "sentBy": "attack-bot-skip",
      "sentAt": 1778496260152
    },
    {
      "id": "3790_13270_1778786621000",
      "originId": "3790",
      "targetId": "13270",
      "slowest": "catapult",
      "arrivalMs": 1778786621000,
      "catapultTarget": "14",
      "troops": {
        "spear": 0,
        "sword": 0,
        "axe": 0,
        "archer": 0,
        "spy": 1,
        "light": 0,
        "marcher": 0,
        "heavy": 0,
        "ram": 0,
        "catapult": 9,
        "knight": 0,
        "snob": 0,
        "militia": 0
      },
      "sent": true,
      "sentBy": "attack-bot-skip",
      "sentAt": 1778496255230
    },
    {
      "id": "2171_4738_1778785740000",
      "originId": "2171",
      "targetId": "4738",
      "slowest": "catapult",
      "arrivalMs": 1778785740000,
      "catapultTarget": "14",
      "troops": {
        "spear": 0,
        "sword": 0,
        "axe": 0,
        "archer": 0,
        "spy": 1,
        "light": 0,
        "marcher": 0,
        "heavy": 0,
        "ram": 0,
        "catapult": 9,
        "knight": 0,
        "snob": 0,
        "militia": 0
      },
      "sent": true,
      "sentBy": "attack-bot-skip",
      "sentAt": 1778496259027
    },
    {
      "id": "3790_2961_1778786997000",
      "originId": "3790",
      "targetId": "2961",
      "slowest": "catapult",
      "arrivalMs": 1778786997000,
      "catapultTarget": "14",
      "troops": {
        "spear": 0,
        "sword": 0,
        "axe": 0,
        "archer": 0,
        "spy": 1,
        "light": 0,
        "marcher": 0,
        "heavy": 0,
        "ram": 0,
        "catapult": 9,
        "knight": 0,
        "snob": 0,
        "militia": 0
      },
      "sent": true,
      "sentBy": "attack-bot-skip",
      "sentAt": 1778496257768
    },
    {
      "id": "379_10225_1778787763000",
      "originId": "379",
      "targetId": "10225",
      "slowest": "catapult",
      "arrivalMs": 1778787763000,
      "catapultTarget": "14",
      "troops": {
        "spear": 0,
        "sword": 0,
        "axe": 0,
        "archer": 0,
        "spy": 1,
        "light": 0,
        "marcher": 0,
        "heavy": 0,
        "ram": 0,
        "catapult": 5,
        "knight": 0,
        "snob": 0,
        "militia": 0
      },
      "sent": true,
      "sentBy": "attack-bot-skip",
      "sentAt": 1778496253927
    },
    {
      "id": "379_5295_1778785699000",
      "originId": "379",
      "targetId": "5295",
      "slowest": "catapult",
      "arrivalMs": 1778785699000,
      "catapultTarget": "14",
      "troops": {
        "spear": 0,
        "sword": 0,
        "axe": 0,
        "archer": 0,
        "spy": 1,
        "light": 0,
        "marcher": 0,
        "heavy": 0,
        "ram": 0,
        "catapult": 5,
        "knight": 0,
        "snob": 0,
        "militia": 0
      },
      "sent": true,
      "sentBy": "attack-bot-skip",
      "sentAt": 1778496272785
    },
    {
      "id": "379_2875_1778786390000",
      "originId": "379",
      "targetId": "2875",
      "slowest": "catapult",
      "arrivalMs": 1778786390000,
      "catapultTarget": "14",
      "troops": {
        "spear": 0,
        "sword": 0,
        "axe": 0,
        "archer": 0,
        "spy": 1,
        "light": 0,
        "marcher": 0,
        "heavy": 0,
        "ram": 0,
        "catapult": 5,
        "knight": 0,
        "snob": 0,
        "militia": 0
      },
      "sent": true,
      "sentBy": "attack-bot-skip",
      "sentAt": 1778496261588
    },
    {
      "id": "4628_6969_1778785264000",
      "originId": "4628",
      "targetId": "6969",
      "slowest": "catapult",
      "arrivalMs": 1778785264000,
      "catapultTarget": "14",
      "troops": {
        "spear": 0,
        "sword": 0,
        "axe": 0,
        "archer": 0,
        "spy": 1,
        "light": 0,
        "marcher": 0,
        "heavy": 0,
        "ram": 0,
        "catapult": 12,
        "knight": 0,
        "snob": 0,
        "militia": 0
      },
      "sent": true,
      "sentBy": "attack-bot-skip",
      "sentAt": 1778496275657
    },
    {
      "id": "379_5482_1778785627000",
      "originId": "379",
      "targetId": "5482",
      "slowest": "catapult",
      "arrivalMs": 1778785627000,
      "catapultTarget": "14",
      "troops": {
        "spear": 0,
        "sword": 0,
        "axe": 0,
        "archer": 0,
        "spy": 1,
        "light": 0,
        "marcher": 0,
        "heavy": 0,
        "ram": 0,
        "catapult": 5,
        "knight": 0,
        "snob": 0,
        "militia": 0
      },
      "sent": true,
      "sentBy": "attack-bot-skip",
      "sentAt": 1778496274128
    },
    {
      "id": "3790_22130_1778785228000",
      "originId": "3790",
      "targetId": "22130",
      "slowest": "catapult",
      "arrivalMs": 1778785228000,
      "catapultTarget": "14",
      "troops": {
        "spear": 0,
        "sword": 0,
        "axe": 0,
        "archer": 0,
        "spy": 1,
        "light": 0,
        "marcher": 0,
        "heavy": 0,
        "ram": 0,
        "catapult": 9,
        "knight": 0,
        "snob": 0,
        "militia": 0
      },
      "sent": true,
      "sentBy": "attack-bot-skip",
      "sentAt": 1778496282392
    },
    {
      "id": "2171_3_1778785443000",
      "originId": "2171",
      "targetId": "3",
      "slowest": "catapult",
      "arrivalMs": 1778785443000,
      "catapultTarget": "14",
      "troops": {
        "spear": 0,
        "sword": 0,
        "axe": 0,
        "archer": 0,
        "spy": 1,
        "light": 0,
        "marcher": 0,
        "heavy": 0,
        "ram": 0,
        "catapult": 9,
        "knight": 0,
        "snob": 0,
        "militia": 0
      },
      "sent": true,
      "sentBy": "attack-bot-skip",
      "sentAt": 1778496286254
    },
    {
      "id": "2171_4832_1778785710000",
      "originId": "2171",
      "targetId": "4832",
      "slowest": "catapult",
      "arrivalMs": 1778785710000,
      "catapultTarget": "14",
      "troops": {
        "spear": 0,
        "sword": 0,
        "axe": 0,
        "archer": 0,
        "spy": 1,
        "light": 0,
        "marcher": 0,
        "heavy": 0,
        "ram": 0,
        "catapult": 9,
        "knight": 0,
        "snob": 0,
        "militia": 0
      },
      "sent": true,
      "sentBy": "attack-bot-skip",
      "sentAt": 1778496291519
    },
    {
      "id": "379_6594_1778785941000",
      "originId": "379",
      "targetId": "6594",
      "slowest": "catapult",
      "arrivalMs": 1778785941000,
      "catapultTarget": "14",
      "troops": {
        "spear": 0,
        "sword": 0,
        "axe": 0,
        "archer": 0,
        "spy": 1,
        "light": 0,
        "marcher": 0,
        "heavy": 0,
        "ram": 0,
        "catapult": 5,
        "knight": 0,
        "snob": 0,
        "militia": 0
      },
      "sent": true,
      "sentBy": "attack-bot-skip",
      "sentAt": 1778496285050
    },
    {
      "id": "3790_6559_1778787288000",
      "originId": "3790",
      "targetId": "6559",
      "slowest": "catapult",
      "arrivalMs": 1778787288000,
      "catapultTarget": "14",
      "troops": {
        "spear": 0,
        "sword": 0,
        "axe": 0,
        "archer": 0,
        "spy": 1,
        "light": 0,
        "marcher": 0,
        "heavy": 0,
        "ram": 0,
        "catapult": 9,
        "knight": 0,
        "snob": 0,
        "militia": 0
      },
      "sent": true,
      "sentBy": "attack-bot-skip",
      "sentAt": 1778496266458
    },
    {
      "id": "2171_2139_1778786822000",
      "originId": "2171",
      "targetId": "2139",
      "slowest": "catapult",
      "arrivalMs": 1778786822000,
      "catapultTarget": "14",
      "troops": {
        "spear": 0,
        "sword": 0,
        "axe": 0,
        "archer": 0,
        "spy": 1,
        "light": 0,
        "marcher": 0,
        "heavy": 0,
        "ram": 0,
        "catapult": 9,
        "knight": 0,
        "snob": 0,
        "militia": 0
      },
      "sent": true,
      "sentBy": "attack-bot-skip",
      "sentAt": 1778496267722
    },
    {
      "id": "4628_6373_1778785242000",
      "originId": "4628",
      "targetId": "6373",
      "slowest": "catapult",
      "arrivalMs": 1778785242000,
      "catapultTarget": "14",
      "troops": {
        "spear": 0,
        "sword": 0,
        "axe": 0,
        "archer": 0,
        "spy": 1,
        "light": 0,
        "marcher": 0,
        "heavy": 0,
        "ram": 0,
        "catapult": 12,
        "knight": 0,
        "snob": 0,
        "militia": 0
      },
      "sent": true,
      "sentBy": "attack-bot-skip",
      "sentAt": 1778496299106
    },
    {
      "id": "2171_6582_1778785200000",
      "originId": "2171",
      "targetId": "6582",
      "slowest": "catapult",
      "arrivalMs": 1778785200000,
      "catapultTarget": "14",
      "troops": {
        "spear": 0,
        "sword": 0,
        "axe": 0,
        "archer": 0,
        "spy": 1,
        "light": 0,
        "marcher": 0,
        "heavy": 0,
        "ram": 0,
        "catapult": 9,
        "knight": 0,
        "snob": 0,
        "militia": 0
      },
      "sent": true,
      "sentBy": "attack-bot-skip",
      "sentAt": 1778496300584
    },
    {
      "id": "4628_5895_1778785264000",
      "originId": "4628",
      "targetId": "5895",
      "slowest": "catapult",
      "arrivalMs": 1778785264000,
      "catapultTarget": "14",
      "troops": {
        "spear": 0,
        "sword": 0,
        "axe": 0,
        "archer": 0,
        "spy": 1,
        "light": 0,
        "marcher": 0,
        "heavy": 0,
        "ram": 0,
        "catapult": 12,
        "knight": 0,
        "snob": 0,
        "militia": 0
      },
      "sent": true,
      "sentBy": "attack-bot-skip",
      "sentAt": 1778496301798
    },
    {
      "id": "3790_1580_1778785770000",
      "originId": "3790",
      "targetId": "1580",
      "slowest": "catapult",
      "arrivalMs": 1778785770000,
      "catapultTarget": "14",
      "troops": {
        "spear": 0,
        "sword": 0,
        "axe": 0,
        "archer": 0,
        "spy": 1,
        "light": 0,
        "marcher": 0,
        "heavy": 0,
        "ram": 0,
        "catapult": 9,
        "knight": 0,
        "snob": 0,
        "militia": 0
      },
      "sent": true,
      "sentBy": "attack-bot-skip",
      "sentAt": 1778496294178
    },
    {
      "id": "4628_3350_1778785202000",
      "originId": "4628",
      "targetId": "3350",
      "slowest": "catapult",
      "arrivalMs": 1778785202000,
      "catapultTarget": "14",
      "troops": {
        "spear": 0,
        "sword": 0,
        "axe": 0,
        "archer": 0,
        "spy": 1,
        "light": 0,
        "marcher": 0,
        "heavy": 0,
        "ram": 0,
        "catapult": 12,
        "knight": 0,
        "snob": 0,
        "militia": 0
      },
      "sent": true,
      "sentBy": "attack-bot-skip",
      "sentAt": 1778496306348
    },
    {
      "id": "3907_9384_1778785223000",
      "originId": "3907",
      "targetId": "9384",
      "slowest": "catapult",
      "arrivalMs": 1778785223000,
      "catapultTarget": "14",
      "troops": {
        "spear": 0,
        "sword": 0,
        "axe": 0,
        "archer": 0,
        "spy": 1,
        "light": 0,
        "marcher": 0,
        "heavy": 0,
        "ram": 0,
        "catapult": 9,
        "knight": 0,
        "snob": 0,
        "militia": 0
      },
      "sent": true,
      "sentBy": "attack-bot-skip",
      "sentAt": 1778496308854
    },
    {
      "id": "4628_12809_1778786443000",
      "originId": "4628",
      "targetId": "12809",
      "slowest": "catapult",
      "arrivalMs": 1778786443000,
      "catapultTarget": "14",
      "troops": {
        "spear": 0,
        "sword": 0,
        "axe": 0,
        "archer": 0,
        "spy": 1,
        "light": 0,
        "marcher": 0,
        "heavy": 0,
        "ram": 0,
        "catapult": 12,
        "knight": 0,
        "snob": 0,
        "militia": 0
      },
      "sent": true,
      "sentBy": "attack-bot-skip",
      "sentAt": 1778496280933
    },
    {
      "id": "2171_4412_1778785277000",
      "originId": "2171",
      "targetId": "4412",
      "slowest": "catapult",
      "arrivalMs": 1778785277000,
      "catapultTarget": "14",
      "troops": {
        "spear": 0,
        "sword": 0,
        "axe": 0,
        "archer": 0,
        "spy": 1,
        "light": 0,
        "marcher": 0,
        "heavy": 0,
        "ram": 0,
        "catapult": 9,
        "knight": 0,
        "snob": 0,
        "militia": 0
      },
      "sent": true,
      "sentBy": "attack-bot-skip",
      "sentAt": 1778496307828
    },
    {
      "id": "2171_3876_1778785413000",
      "originId": "2171",
      "targetId": "3876",
      "slowest": "catapult",
      "arrivalMs": 1778785413000,
      "catapultTarget": "14",
      "troops": {
        "spear": 0,
        "sword": 0,
        "axe": 0,
        "archer": 0,
        "spy": 1,
        "light": 0,
        "marcher": 0,
        "heavy": 0,
        "ram": 0,
        "catapult": 9,
        "knight": 0,
        "snob": 0,
        "militia": 0
      },
      "sent": true,
      "sentBy": "attack-bot-skip",
      "sentAt": 1778496303316
    },
    {
      "id": "2171_2840_1778786194000",
      "originId": "2171",
      "targetId": "2840",
      "slowest": "catapult",
      "arrivalMs": 1778786194000,
      "catapultTarget": "14",
      "troops": {
        "spear": 0,
        "sword": 0,
        "axe": 0,
        "archer": 0,
        "spy": 1,
        "light": 0,
        "marcher": 0,
        "heavy": 0,
        "ram": 0,
        "catapult": 9,
        "knight": 0,
        "snob": 0,
        "militia": 0
      },
      "sent": true,
      "sentBy": "attack-bot-skip",
      "sentAt": 1778496292728
    },
    {
      "id": "4628_13461_1778786440000",
      "originId": "4628",
      "targetId": "13461",
      "slowest": "catapult",
      "arrivalMs": 1778786440000,
      "catapultTarget": "14",
      "troops": {
        "spear": 0,
        "sword": 0,
        "axe": 0,
        "archer": 0,
        "spy": 1,
        "light": 0,
        "marcher": 0,
        "heavy": 0,
        "ram": 0,
        "catapult": 12,
        "knight": 0,
        "snob": 0,
        "militia": 0
      },
      "sent": true,
      "sentBy": "attack-bot-skip",
      "sentAt": 1778496283646
    },
    {
      "id": "379_4773_1778785509000",
      "originId": "379",
      "targetId": "4773",
      "slowest": "catapult",
      "arrivalMs": 1778785509000,
      "catapultTarget": "14",
      "troops": {
        "spear": 0,
        "sword": 0,
        "axe": 0,
        "archer": 0,
        "spy": 1,
        "light": 0,
        "marcher": 0,
        "heavy": 0,
        "ram": 0,
        "catapult": 5,
        "knight": 0,
        "snob": 0,
        "militia": 0
      },
      "sent": true,
      "sentBy": "attack-bot-skip",
      "sentAt": 1778496304522
    },
    {
      "id": "4628_8444_1778785208000",
      "originId": "4628",
      "targetId": "8444",
      "slowest": "catapult",
      "arrivalMs": 1778785208000,
      "catapultTarget": "14",
      "troops": {
        "spear": 0,
        "sword": 0,
        "axe": 0,
        "archer": 0,
        "spy": 1,
        "light": 0,
        "marcher": 0,
        "heavy": 0,
        "ram": 0,
        "catapult": 12,
        "knight": 0,
        "snob": 0,
        "militia": 0
      },
      "sent": true,
      "sentBy": "attack-bot-skip",
      "sentAt": 1778496310479
    },
    {
      "id": "3907_1261_1778785209000",
      "originId": "3907",
      "targetId": "1261",
      "slowest": "catapult",
      "arrivalMs": 1778785209000,
      "catapultTarget": "14",
      "troops": {
        "spear": 0,
        "sword": 0,
        "axe": 0,
        "archer": 0,
        "spy": 1,
        "light": 0,
        "marcher": 0,
        "heavy": 0,
        "ram": 0,
        "catapult": 9,
        "knight": 0,
        "snob": 0,
        "militia": 0
      },
      "sent": true,
      "sentBy": "attack-bot-skip",
      "sentAt": 1778496315563
    },
    {
      "id": "4628_1985_1778792022000",
      "originId": "4628",
      "targetId": "1985",
      "slowest": "catapult",
      "arrivalMs": 1778792022000,
      "catapultTarget": "14",
      "troops": {
        "spear": 0,
        "sword": 0,
        "axe": 0,
        "archer": 0,
        "spy": 1,
        "light": 0,
        "marcher": 0,
        "heavy": 0,
        "ram": 0,
        "catapult": 12,
        "knight": 0,
        "snob": 0,
        "militia": 0
      },
      "sent": true,
      "sentBy": "attack-bot-skip",
      "sentAt": 1778496316986
    },
    {
      "id": "3790_11823_1778791301000",
      "originId": "3790",
      "targetId": "11823",
      "slowest": "catapult",
      "arrivalMs": 1778791301000,
      "catapultTarget": "14",
      "troops": {
        "spear": 0,
        "sword": 0,
        "axe": 0,
        "archer": 0,
        "spy": 1,
        "light": 0,
        "marcher": 0,
        "heavy": 0,
        "ram": 0,
        "catapult": 9,
        "knight": 0,
        "snob": 0,
        "militia": 0
      },
      "sent": true,
      "sentBy": "attack-bot-skip",
      "sentAt": 1778496320881
    },
    {
      "id": "3907_2563_1778792032000",
      "originId": "3907",
      "targetId": "2563",
      "slowest": "catapult",
      "arrivalMs": 1778792032000,
      "catapultTarget": "14",
      "troops": {
        "spear": 0,
        "sword": 0,
        "axe": 0,
        "archer": 0,
        "spy": 1,
        "light": 0,
        "marcher": 0,
        "heavy": 0,
        "ram": 0,
        "catapult": 9,
        "knight": 0,
        "snob": 0,
        "militia": 0
      },
      "sent": true,
      "sentBy": "attack-bot-skip",
      "sentAt": 1778496318311
    },
    {
      "id": "3790_9781_1778792010000",
      "originId": "3790",
      "targetId": "9781",
      "slowest": "catapult",
      "arrivalMs": 1778792010000,
      "catapultTarget": "14",
      "troops": {
        "spear": 0,
        "sword": 0,
        "axe": 0,
        "archer": 0,
        "spy": 1,
        "light": 0,
        "marcher": 0,
        "heavy": 0,
        "ram": 0,
        "catapult": 9,
        "knight": 0,
        "snob": 0,
        "militia": 0
      },
      "sent": true,
      "sentBy": "attack-bot-skip",
      "sentAt": 1778496319487
    },
    {
      "id": "3907_15525_1778788579000",
      "originId": "3907",
      "targetId": "15525",
      "slowest": "catapult",
      "arrivalMs": 1778788579000,
      "catapultTarget": "14",
      "troops": {
        "spear": 0,
        "sword": 0,
        "axe": 0,
        "archer": 0,
        "spy": 1,
        "light": 0,
        "marcher": 0,
        "heavy": 0,
        "ram": 0,
        "catapult": 9,
        "knight": 0,
        "snob": 0,
        "militia": 0
      },
      "sent": true,
      "sentBy": "attack-bot-skip",
      "sentAt": 1778496322451
    },
    {
      "id": "4458_6057_1778785288000",
      "originId": "4458",
      "targetId": "6057",
      "slowest": "catapult",
      "arrivalMs": 1778785288000,
      "catapultTarget": "14",
      "troops": {
        "spear": 0,
        "sword": 0,
        "axe": 0,
        "archer": 0,
        "spy": 1,
        "light": 0,
        "marcher": 0,
        "heavy": 0,
        "ram": 0,
        "catapult": 6,
        "knight": 0,
        "snob": 0,
        "militia": 0
      },
      "sent": true,
      "sentBy": "attack-bot-skip",
      "sentAt": 1778496323678
    },
    {
      "id": "4458_3171_1778785581000",
      "originId": "4458",
      "targetId": "3171",
      "slowest": "catapult",
      "arrivalMs": 1778785581000,
      "catapultTarget": "14",
      "troops": {
        "spear": 0,
        "sword": 0,
        "axe": 0,
        "archer": 0,
        "spy": 1,
        "light": 0,
        "marcher": 0,
        "heavy": 0,
        "ram": 0,
        "catapult": 6,
        "knight": 0,
        "snob": 0,
        "militia": 0
      },
      "sent": true,
      "sentBy": "attack-bot-skip",
      "sentAt": 1778496328717
    },
    {
      "id": "3907_18705_1778785715000",
      "originId": "3907",
      "targetId": "18705",
      "slowest": "catapult",
      "arrivalMs": 1778785715000,
      "catapultTarget": "14",
      "troops": {
        "spear": 0,
        "sword": 0,
        "axe": 0,
        "archer": 0,
        "spy": 1,
        "light": 0,
        "marcher": 0,
        "heavy": 0,
        "ram": 0,
        "catapult": 9,
        "knight": 0,
        "snob": 0,
        "militia": 0
      },
      "sent": true,
      "sentBy": "attack-bot-skip",
      "sentAt": 1778496330182
    },
    {
      "id": "3907_16749_1778792097000",
      "originId": "3907",
      "targetId": "16749",
      "slowest": "catapult",
      "arrivalMs": 1778792097000,
      "catapultTarget": "14",
      "troops": {
        "spear": 0,
        "sword": 0,
        "axe": 0,
        "archer": 0,
        "spy": 1,
        "light": 0,
        "marcher": 0,
        "heavy": 0,
        "ram": 0,
        "catapult": 9,
        "knight": 0,
        "snob": 0,
        "militia": 0
      },
      "sent": true,
      "sentBy": "attack-bot-skip",
      "sentAt": 1778496335163
    },
    {
      "id": "4458_7034_1778791861000",
      "originId": "4458",
      "targetId": "7034",
      "slowest": "catapult",
      "arrivalMs": 1778791861000,
      "catapultTarget": "14",
      "troops": {
        "spear": 0,
        "sword": 0,
        "axe": 0,
        "archer": 0,
        "spy": 1,
        "light": 0,
        "marcher": 0,
        "heavy": 0,
        "ram": 0,
        "catapult": 6,
        "knight": 0,
        "snob": 0,
        "militia": 0
      },
      "sent": true,
      "sentBy": "attack-bot-skip",
      "sentAt": 1778496339257
    },
    {
      "id": "4458_6377_1778792070000",
      "originId": "4458",
      "targetId": "6377",
      "slowest": "catapult",
      "arrivalMs": 1778792070000,
      "catapultTarget": "14",
      "troops": {
        "spear": 0,
        "sword": 0,
        "axe": 0,
        "archer": 0,
        "spy": 1,
        "light": 0,
        "marcher": 0,
        "heavy": 0,
        "ram": 0,
        "catapult": 6,
        "knight": 0,
        "snob": 0,
        "militia": 0
      },
      "sent": true,
      "sentBy": "attack-bot-skip",
      "sentAt": 1778496337940
    },
    {
      "id": "3907_14356_1778792098000",
      "originId": "3907",
      "targetId": "14356",
      "slowest": "catapult",
      "arrivalMs": 1778792098000,
      "catapultTarget": "14",
      "troops": {
        "spear": 0,
        "sword": 0,
        "axe": 0,
        "archer": 0,
        "spy": 1,
        "light": 0,
        "marcher": 0,
        "heavy": 0,
        "ram": 0,
        "catapult": 9,
        "knight": 0,
        "snob": 0,
        "militia": 0
      },
      "sent": true,
      "sentBy": "attack-bot-skip",
      "sentAt": 1778496336568
    },
    {
      "id": "3907_14259_1778791434000",
      "originId": "3907",
      "targetId": "14259",
      "slowest": "catapult",
      "arrivalMs": 1778791434000,
      "catapultTarget": "14",
      "troops": {
        "spear": 0,
        "sword": 0,
        "axe": 0,
        "archer": 0,
        "spy": 1,
        "light": 0,
        "marcher": 0,
        "heavy": 0,
        "ram": 0,
        "catapult": 9,
        "knight": 0,
        "snob": 0,
        "militia": 0
      },
      "sent": true,
      "sentBy": "attack-bot-skip",
      "sentAt": 1778496340528
    },
    {
      "id": "5828_9224_1778789320000",
      "originId": "5828",
      "targetId": "9224",
      "slowest": "catapult",
      "arrivalMs": 1778789320000,
      "catapultTarget": "14",
      "troops": {
        "spear": 0,
        "sword": 0,
        "axe": 0,
        "archer": 0,
        "spy": 1,
        "light": 0,
        "marcher": 0,
        "heavy": 0,
        "ram": 0,
        "catapult": 8,
        "knight": 0,
        "snob": 0,
        "militia": 0
      },
      "sent": true,
      "sentBy": "attack-bot-skip",
      "sentAt": 1778496341797
    },
    {
      "id": "5828_10991_1778785229000",
      "originId": "5828",
      "targetId": "10991",
      "slowest": "catapult",
      "arrivalMs": 1778785229000,
      "catapultTarget": "14",
      "troops": {
        "spear": 0,
        "sword": 0,
        "axe": 0,
        "archer": 0,
        "spy": 1,
        "light": 0,
        "marcher": 0,
        "heavy": 0,
        "ram": 0,
        "catapult": 8,
        "knight": 0,
        "snob": 0,
        "militia": 0
      },
      "sent": true,
      "sentBy": "attack-bot-skip",
      "sentAt": 1778496347364
    },
    {
      "id": "5828_9322_1778785824000",
      "originId": "5828",
      "targetId": "9322",
      "slowest": "catapult",
      "arrivalMs": 1778785824000,
      "catapultTarget": "14",
      "troops": {
        "spear": 0,
        "sword": 0,
        "axe": 0,
        "archer": 0,
        "spy": 1,
        "light": 0,
        "marcher": 0,
        "heavy": 0,
        "ram": 0,
        "catapult": 8,
        "knight": 0,
        "snob": 0,
        "militia": 0
      },
      "sent": true,
      "sentBy": "attack-bot-skip",
      "sentAt": 1778496345920
    },
    {
      "id": "5828_11024_1778790405000",
      "originId": "5828",
      "targetId": "11024",
      "slowest": "catapult",
      "arrivalMs": 1778790405000,
      "catapultTarget": "14",
      "troops": {
        "spear": 0,
        "sword": 0,
        "axe": 0,
        "archer": 0,
        "spy": 1,
        "light": 0,
        "marcher": 0,
        "heavy": 0,
        "ram": 0,
        "catapult": 8,
        "knight": 0,
        "snob": 0,
        "militia": 0
      },
      "sent": true,
      "sentBy": "attack-bot-skip",
      "sentAt": 1778496343162
    },
    {
      "id": "5177_6350_1778785904000",
      "originId": "5177",
      "targetId": "6350",
      "slowest": "catapult",
      "arrivalMs": 1778785904000,
      "catapultTarget": "14",
      "troops": {
        "spear": 0,
        "sword": 0,
        "axe": 0,
        "archer": 0,
        "spy": 1,
        "light": 0,
        "marcher": 0,
        "heavy": 0,
        "ram": 0,
        "catapult": 5,
        "knight": 0,
        "snob": 0,
        "militia": 0
      },
      "sent": true,
      "sentBy": "attack-bot-skip",
      "sentAt": 1778496349042
    },
    {
      "id": "5177_6606_1778785397000",
      "originId": "5177",
      "targetId": "6606",
      "slowest": "catapult",
      "arrivalMs": 1778785397000,
      "catapultTarget": "14",
      "troops": {
        "spear": 0,
        "sword": 0,
        "axe": 0,
        "archer": 0,
        "spy": 1,
        "light": 0,
        "marcher": 0,
        "heavy": 0,
        "ram": 0,
        "catapult": 5,
        "knight": 0,
        "snob": 0,
        "militia": 0
      },
      "sent": true,
      "sentBy": "attack-bot-skip",
      "sentAt": 1778496350379
    },
    {
      "id": "5828_10134_1778789824000",
      "originId": "5828",
      "targetId": "10134",
      "slowest": "catapult",
      "arrivalMs": 1778789824000,
      "catapultTarget": "14",
      "troops": {
        "spear": 0,
        "sword": 0,
        "axe": 0,
        "archer": 0,
        "spy": 1,
        "light": 0,
        "marcher": 0,
        "heavy": 0,
        "ram": 0,
        "catapult": 8,
        "knight": 0,
        "snob": 0,
        "militia": 0
      },
      "sent": true,
      "sentBy": "attack-bot-skip",
      "sentAt": 1778496344626
    },
    {
      "id": "5177_4694_1778785320000",
      "originId": "5177",
      "targetId": "4694",
      "slowest": "catapult",
      "arrivalMs": 1778785320000,
      "catapultTarget": "14",
      "troops": {
        "spear": 0,
        "sword": 0,
        "axe": 0,
        "archer": 0,
        "spy": 1,
        "light": 0,
        "marcher": 0,
        "heavy": 0,
        "ram": 0,
        "catapult": 5,
        "knight": 0,
        "snob": 0,
        "militia": 0
      },
      "sent": true,
      "sentBy": "attack-bot-skip",
      "sentAt": 1778496355690
    },
    {
      "id": "5177_5993_1778785317000",
      "originId": "5177",
      "targetId": "5993",
      "slowest": "catapult",
      "arrivalMs": 1778785317000,
      "catapultTarget": "14",
      "troops": {
        "spear": 0,
        "sword": 0,
        "axe": 0,
        "archer": 0,
        "spy": 1,
        "light": 0,
        "marcher": 0,
        "heavy": 0,
        "ram": 0,
        "catapult": 5,
        "knight": 0,
        "snob": 0,
        "militia": 0
      },
      "sent": false,
      "sentBy": null,
      "sentAt": null
    },
    {
      "id": "5177_5188_1778791833000",
      "originId": "5177",
      "targetId": "5188",
      "slowest": "catapult",
      "arrivalMs": 1778791833000,
      "catapultTarget": "14",
      "troops": {
        "spear": 0,
        "sword": 0,
        "axe": 0,
        "archer": 0,
        "spy": 1,
        "light": 0,
        "marcher": 0,
        "heavy": 0,
        "ram": 0,
        "catapult": 5,
        "knight": 0,
        "snob": 0,
        "militia": 0
      },
      "sent": false,
      "sentBy": null,
      "sentAt": null
    },
    {
      "id": "5177_4609_1778789790000",
      "originId": "5177",
      "targetId": "4609",
      "slowest": "catapult",
      "arrivalMs": 1778789790000,
      "catapultTarget": "14",
      "troops": {
        "spear": 0,
        "sword": 0,
        "axe": 0,
        "archer": 0,
        "spy": 1,
        "light": 0,
        "marcher": 0,
        "heavy": 0,
        "ram": 0,
        "catapult": 5,
        "knight": 0,
        "snob": 0,
        "militia": 0
      },
      "sent": false,
      "sentBy": null,
      "sentAt": null
    },
    {
      "id": "8805_13192_1778788488000",
      "originId": "8805",
      "targetId": "13192",
      "slowest": "catapult",
      "arrivalMs": 1778788488000,
      "catapultTarget": "14",
      "troops": {
        "spear": 0,
        "sword": 0,
        "axe": 0,
        "archer": 0,
        "spy": 1,
        "light": 0,
        "marcher": 0,
        "heavy": 0,
        "ram": 0,
        "catapult": 4,
        "knight": 0,
        "snob": 0,
        "militia": 0
      },
      "sent": false,
      "sentBy": null,
      "sentAt": null
    },
    {
      "id": "8805_7822_1778791296000",
      "originId": "8805",
      "targetId": "7822",
      "slowest": "catapult",
      "arrivalMs": 1778791296000,
      "catapultTarget": "14",
      "troops": {
        "spear": 0,
        "sword": 0,
        "axe": 0,
        "archer": 0,
        "spy": 1,
        "light": 0,
        "marcher": 0,
        "heavy": 0,
        "ram": 0,
        "catapult": 4,
        "knight": 0,
        "snob": 0,
        "militia": 0
      },
      "sent": false,
      "sentBy": null,
      "sentAt": null
    },
    {
      "id": "4885_11056_1778785374000",
      "originId": "4885",
      "targetId": "11056",
      "slowest": "catapult",
      "arrivalMs": 1778785374000,
      "catapultTarget": "14",
      "troops": {
        "spear": 0,
        "sword": 0,
        "axe": 0,
        "archer": 0,
        "spy": 1,
        "light": 0,
        "marcher": 0,
        "heavy": 0,
        "ram": 0,
        "catapult": 13,
        "knight": 0,
        "snob": 0,
        "militia": 0
      },
      "sent": false,
      "sentBy": null,
      "sentAt": null
    },
    {
      "id": "5177_3461_1778790228000",
      "originId": "5177",
      "targetId": "3461",
      "slowest": "catapult",
      "arrivalMs": 1778790228000,
      "catapultTarget": "14",
      "troops": {
        "spear": 0,
        "sword": 0,
        "axe": 0,
        "archer": 0,
        "spy": 1,
        "light": 0,
        "marcher": 0,
        "heavy": 0,
        "ram": 0,
        "catapult": 5,
        "knight": 0,
        "snob": 0,
        "militia": 0
      },
      "sent": false,
      "sentBy": null,
      "sentAt": null
    },
    {
      "id": "4885_3987_1778785975000",
      "originId": "4885",
      "targetId": "3987",
      "slowest": "catapult",
      "arrivalMs": 1778785975000,
      "catapultTarget": "14",
      "troops": {
        "spear": 0,
        "sword": 0,
        "axe": 0,
        "archer": 0,
        "spy": 1,
        "light": 0,
        "marcher": 0,
        "heavy": 0,
        "ram": 0,
        "catapult": 13,
        "knight": 0,
        "snob": 0,
        "militia": 0
      },
      "sent": false,
      "sentBy": null,
      "sentAt": null
    },
    {
      "id": "5177_794_1778791291000",
      "originId": "5177",
      "targetId": "794",
      "slowest": "catapult",
      "arrivalMs": 1778791291000,
      "catapultTarget": "14",
      "troops": {
        "spear": 0,
        "sword": 0,
        "axe": 0,
        "archer": 0,
        "spy": 1,
        "light": 0,
        "marcher": 0,
        "heavy": 0,
        "ram": 0,
        "catapult": 5,
        "knight": 0,
        "snob": 0,
        "militia": 0
      },
      "sent": false,
      "sentBy": null,
      "sentAt": null
    },
    {
      "id": "2618_9512_1778790071000",
      "originId": "2618",
      "targetId": "9512",
      "slowest": "catapult",
      "arrivalMs": 1778790071000,
      "catapultTarget": "14",
      "troops": {
        "spear": 0,
        "sword": 0,
        "axe": 0,
        "archer": 0,
        "spy": 1,
        "light": 0,
        "marcher": 0,
        "heavy": 0,
        "ram": 0,
        "catapult": 7,
        "knight": 0,
        "snob": 0,
        "militia": 0
      },
      "sent": false,
      "sentBy": null,
      "sentAt": null
    },
    {
      "id": "2618_7649_1778786537000",
      "originId": "2618",
      "targetId": "7649",
      "slowest": "catapult",
      "arrivalMs": 1778786537000,
      "catapultTarget": "14",
      "troops": {
        "spear": 0,
        "sword": 0,
        "axe": 0,
        "archer": 0,
        "spy": 1,
        "light": 0,
        "marcher": 0,
        "heavy": 0,
        "ram": 0,
        "catapult": 7,
        "knight": 0,
        "snob": 0,
        "militia": 0
      },
      "sent": false,
      "sentBy": null,
      "sentAt": null
    },
    {
      "id": "8805_8498_1778790811000",
      "originId": "8805",
      "targetId": "8498",
      "slowest": "catapult",
      "arrivalMs": 1778790811000,
      "catapultTarget": "14",
      "troops": {
        "spear": 0,
        "sword": 0,
        "axe": 0,
        "archer": 0,
        "spy": 1,
        "light": 0,
        "marcher": 0,
        "heavy": 0,
        "ram": 0,
        "catapult": 4,
        "knight": 0,
        "snob": 0,
        "militia": 0
      },
      "sent": false,
      "sentBy": null,
      "sentAt": null
    },
    {
      "id": "8805_13467_1778789495000",
      "originId": "8805",
      "targetId": "13467",
      "slowest": "catapult",
      "arrivalMs": 1778789495000,
      "catapultTarget": "14",
      "troops": {
        "spear": 0,
        "sword": 0,
        "axe": 0,
        "archer": 0,
        "spy": 1,
        "light": 0,
        "marcher": 0,
        "heavy": 0,
        "ram": 0,
        "catapult": 4,
        "knight": 0,
        "snob": 0,
        "militia": 0
      },
      "sent": false,
      "sentBy": null,
      "sentAt": null
    },
    {
      "id": "2618_11118_1778787703000",
      "originId": "2618",
      "targetId": "11118",
      "slowest": "catapult",
      "arrivalMs": 1778787703000,
      "catapultTarget": "14",
      "troops": {
        "spear": 0,
        "sword": 0,
        "axe": 0,
        "archer": 0,
        "spy": 1,
        "light": 0,
        "marcher": 0,
        "heavy": 0,
        "ram": 0,
        "catapult": 7,
        "knight": 0,
        "snob": 0,
        "militia": 0
      },
      "sent": false,
      "sentBy": null,
      "sentAt": null
    },
    {
      "id": "4885_5933_1778785719000",
      "originId": "4885",
      "targetId": "5933",
      "slowest": "catapult",
      "arrivalMs": 1778785719000,
      "catapultTarget": "14",
      "troops": {
        "spear": 0,
        "sword": 0,
        "axe": 0,
        "archer": 0,
        "spy": 1,
        "light": 0,
        "marcher": 0,
        "heavy": 0,
        "ram": 0,
        "catapult": 13,
        "knight": 0,
        "snob": 0,
        "militia": 0
      },
      "sent": false,
      "sentBy": null,
      "sentAt": null
    },
    {
      "id": "2618_8673_1778788108000",
      "originId": "2618",
      "targetId": "8673",
      "slowest": "catapult",
      "arrivalMs": 1778788108000,
      "catapultTarget": "14",
      "troops": {
        "spear": 0,
        "sword": 0,
        "axe": 0,
        "archer": 0,
        "spy": 1,
        "light": 0,
        "marcher": 0,
        "heavy": 0,
        "ram": 0,
        "catapult": 7,
        "knight": 0,
        "snob": 0,
        "militia": 0
      },
      "sent": false,
      "sentBy": null,
      "sentAt": null
    },
    {
      "id": "4765_7559_1778785812000",
      "originId": "4765",
      "targetId": "7559",
      "slowest": "catapult",
      "arrivalMs": 1778785812000,
      "catapultTarget": "14",
      "troops": {
        "spear": 0,
        "sword": 0,
        "axe": 0,
        "archer": 0,
        "spy": 1,
        "light": 0,
        "marcher": 0,
        "heavy": 0,
        "ram": 0,
        "catapult": 7,
        "knight": 0,
        "snob": 0,
        "militia": 0
      },
      "sent": false,
      "sentBy": null,
      "sentAt": null
    },
    {
      "id": "8805_13987_1778791433000",
      "originId": "8805",
      "targetId": "13987",
      "slowest": "catapult",
      "arrivalMs": 1778791433000,
      "catapultTarget": "14",
      "troops": {
        "spear": 0,
        "sword": 0,
        "axe": 0,
        "archer": 0,
        "spy": 1,
        "light": 0,
        "marcher": 0,
        "heavy": 0,
        "ram": 0,
        "catapult": 4,
        "knight": 0,
        "snob": 0,
        "militia": 0
      },
      "sent": false,
      "sentBy": null,
      "sentAt": null
    },
    {
      "id": "4765_3638_1778785670000",
      "originId": "4765",
      "targetId": "3638",
      "slowest": "catapult",
      "arrivalMs": 1778785670000,
      "catapultTarget": "14",
      "troops": {
        "spear": 0,
        "sword": 0,
        "axe": 0,
        "archer": 0,
        "spy": 1,
        "light": 0,
        "marcher": 0,
        "heavy": 0,
        "ram": 0,
        "catapult": 7,
        "knight": 0,
        "snob": 0,
        "militia": 0
      },
      "sent": false,
      "sentBy": null,
      "sentAt": null
    },
    {
      "id": "4765_4331_1778786784000",
      "originId": "4765",
      "targetId": "4331",
      "slowest": "catapult",
      "arrivalMs": 1778786784000,
      "catapultTarget": "14",
      "troops": {
        "spear": 0,
        "sword": 0,
        "axe": 0,
        "archer": 0,
        "spy": 1,
        "light": 0,
        "marcher": 0,
        "heavy": 0,
        "ram": 0,
        "catapult": 7,
        "knight": 0,
        "snob": 0,
        "militia": 0
      },
      "sent": false,
      "sentBy": null,
      "sentAt": null
    },
    {
      "id": "4885_8295_1778787392000",
      "originId": "4885",
      "targetId": "8295",
      "slowest": "catapult",
      "arrivalMs": 1778787392000,
      "catapultTarget": "14",
      "troops": {
        "spear": 0,
        "sword": 0,
        "axe": 0,
        "archer": 0,
        "spy": 1,
        "light": 0,
        "marcher": 0,
        "heavy": 0,
        "ram": 0,
        "catapult": 13,
        "knight": 0,
        "snob": 0,
        "militia": 0
      },
      "sent": false,
      "sentBy": null,
      "sentAt": null
    },
    {
      "id": "2618_12429_1778786757000",
      "originId": "2618",
      "targetId": "12429",
      "slowest": "catapult",
      "arrivalMs": 1778786757000,
      "catapultTarget": "14",
      "troops": {
        "spear": 0,
        "sword": 0,
        "axe": 0,
        "archer": 0,
        "spy": 1,
        "light": 0,
        "marcher": 0,
        "heavy": 0,
        "ram": 0,
        "catapult": 7,
        "knight": 0,
        "snob": 0,
        "militia": 0
      },
      "sent": false,
      "sentBy": null,
      "sentAt": null
    },
    {
      "id": "8805_11607_1778791829000",
      "originId": "8805",
      "targetId": "11607",
      "slowest": "catapult",
      "arrivalMs": 1778791829000,
      "catapultTarget": "14",
      "troops": {
        "spear": 0,
        "sword": 0,
        "axe": 0,
        "archer": 0,
        "spy": 1,
        "light": 0,
        "marcher": 0,
        "heavy": 0,
        "ram": 0,
        "catapult": 4,
        "knight": 0,
        "snob": 0,
        "militia": 0
      },
      "sent": false,
      "sentBy": null,
      "sentAt": null
    },
    {
      "id": "2618_9666_1778785476000",
      "originId": "2618",
      "targetId": "9666",
      "slowest": "catapult",
      "arrivalMs": 1778785476000,
      "catapultTarget": "14",
      "troops": {
        "spear": 0,
        "sword": 0,
        "axe": 0,
        "archer": 0,
        "spy": 1,
        "light": 0,
        "marcher": 0,
        "heavy": 0,
        "ram": 0,
        "catapult": 7,
        "knight": 0,
        "snob": 0,
        "militia": 0
      },
      "sent": false,
      "sentBy": null,
      "sentAt": null
    },
    {
      "id": "4885_9484_1778788946000",
      "originId": "4885",
      "targetId": "9484",
      "slowest": "catapult",
      "arrivalMs": 1778788946000,
      "catapultTarget": "14",
      "troops": {
        "spear": 0,
        "sword": 0,
        "axe": 0,
        "archer": 0,
        "spy": 1,
        "light": 0,
        "marcher": 0,
        "heavy": 0,
        "ram": 0,
        "catapult": 13,
        "knight": 0,
        "snob": 0,
        "militia": 0
      },
      "sent": false,
      "sentBy": null,
      "sentAt": null
    },
    {
      "id": "4885_10970_1778787971000",
      "originId": "4885",
      "targetId": "10970",
      "slowest": "catapult",
      "arrivalMs": 1778787971000,
      "catapultTarget": "14",
      "troops": {
        "spear": 0,
        "sword": 0,
        "axe": 0,
        "archer": 0,
        "spy": 1,
        "light": 0,
        "marcher": 0,
        "heavy": 0,
        "ram": 0,
        "catapult": 13,
        "knight": 0,
        "snob": 0,
        "militia": 0
      },
      "sent": false,
      "sentBy": null,
      "sentAt": null
    },
    {
      "id": "4765_3832_1778785463000",
      "originId": "4765",
      "targetId": "3832",
      "slowest": "catapult",
      "arrivalMs": 1778785463000,
      "catapultTarget": "14",
      "troops": {
        "spear": 0,
        "sword": 0,
        "axe": 0,
        "archer": 0,
        "spy": 1,
        "light": 0,
        "marcher": 0,
        "heavy": 0,
        "ram": 0,
        "catapult": 7,
        "knight": 0,
        "snob": 0,
        "militia": 0
      },
      "sent": false,
      "sentBy": null,
      "sentAt": null
    },
    {
      "id": "2507_6381_1778785206000",
      "originId": "2507",
      "targetId": "6381",
      "slowest": "catapult",
      "arrivalMs": 1778785206000,
      "catapultTarget": "14",
      "troops": {
        "spear": 0,
        "sword": 0,
        "axe": 0,
        "archer": 0,
        "spy": 1,
        "light": 0,
        "marcher": 0,
        "heavy": 0,
        "ram": 0,
        "catapult": 8,
        "knight": 0,
        "snob": 0,
        "militia": 0
      },
      "sent": false,
      "sentBy": null,
      "sentAt": null
    },
    {
      "id": "2507_6521_1778785298000",
      "originId": "2507",
      "targetId": "6521",
      "slowest": "catapult",
      "arrivalMs": 1778785298000,
      "catapultTarget": "14",
      "troops": {
        "spear": 0,
        "sword": 0,
        "axe": 0,
        "archer": 0,
        "spy": 1,
        "light": 0,
        "marcher": 0,
        "heavy": 0,
        "ram": 0,
        "catapult": 8,
        "knight": 0,
        "snob": 0,
        "militia": 0
      },
      "sent": false,
      "sentBy": null,
      "sentAt": null
    },
    {
      "id": "2507_6194_1778785208000",
      "originId": "2507",
      "targetId": "6194",
      "slowest": "catapult",
      "arrivalMs": 1778785208000,
      "catapultTarget": "14",
      "troops": {
        "spear": 0,
        "sword": 0,
        "axe": 0,
        "archer": 0,
        "spy": 1,
        "light": 0,
        "marcher": 0,
        "heavy": 0,
        "ram": 0,
        "catapult": 8,
        "knight": 0,
        "snob": 0,
        "militia": 0
      },
      "sent": false,
      "sentBy": null,
      "sentAt": null
    },
    {
      "id": "4885_7795_1778791347000",
      "originId": "4885",
      "targetId": "7795",
      "slowest": "catapult",
      "arrivalMs": 1778791347000,
      "catapultTarget": "14",
      "troops": {
        "spear": 0,
        "sword": 0,
        "axe": 0,
        "archer": 0,
        "spy": 1,
        "light": 0,
        "marcher": 0,
        "heavy": 0,
        "ram": 0,
        "catapult": 13,
        "knight": 0,
        "snob": 0,
        "militia": 0
      },
      "sent": false,
      "sentBy": null,
      "sentAt": null
    },
    {
      "id": "2507_4095_1778789463000",
      "originId": "2507",
      "targetId": "4095",
      "slowest": "catapult",
      "arrivalMs": 1778789463000,
      "catapultTarget": "14",
      "troops": {
        "spear": 0,
        "sword": 0,
        "axe": 0,
        "archer": 0,
        "spy": 1,
        "light": 0,
        "marcher": 0,
        "heavy": 0,
        "ram": 0,
        "catapult": 8,
        "knight": 0,
        "snob": 0,
        "militia": 0
      },
      "sent": false,
      "sentBy": null,
      "sentAt": null
    },
    {
      "id": "2507_5093_1778792001000",
      "originId": "2507",
      "targetId": "5093",
      "slowest": "catapult",
      "arrivalMs": 1778792001000,
      "catapultTarget": "14",
      "troops": {
        "spear": 0,
        "sword": 0,
        "axe": 0,
        "archer": 0,
        "spy": 1,
        "light": 0,
        "marcher": 0,
        "heavy": 0,
        "ram": 0,
        "catapult": 8,
        "knight": 0,
        "snob": 0,
        "militia": 0
      },
      "sent": false,
      "sentBy": null,
      "sentAt": null
    },
    {
      "id": "2618_13664_1778790501000",
      "originId": "2618",
      "targetId": "13664",
      "slowest": "catapult",
      "arrivalMs": 1778790501000,
      "catapultTarget": "14",
      "troops": {
        "spear": 0,
        "sword": 0,
        "axe": 0,
        "archer": 0,
        "spy": 1,
        "light": 0,
        "marcher": 0,
        "heavy": 0,
        "ram": 0,
        "catapult": 7,
        "knight": 0,
        "snob": 0,
        "militia": 0
      },
      "sent": false,
      "sentBy": null,
      "sentAt": null
    },
    {
      "id": "2618_13508_1778792096000",
      "originId": "2618",
      "targetId": "13508",
      "slowest": "catapult",
      "arrivalMs": 1778792096000,
      "catapultTarget": "14",
      "troops": {
        "spear": 0,
        "sword": 0,
        "axe": 0,
        "archer": 0,
        "spy": 1,
        "light": 0,
        "marcher": 0,
        "heavy": 0,
        "ram": 0,
        "catapult": 7,
        "knight": 0,
        "snob": 0,
        "militia": 0
      },
      "sent": false,
      "sentBy": null,
      "sentAt": null
    },
    {
      "id": "12151_7148_1778789687000",
      "originId": "12151",
      "targetId": "7148",
      "slowest": "catapult",
      "arrivalMs": 1778789687000,
      "catapultTarget": "14",
      "troops": {
        "spear": 0,
        "sword": 0,
        "axe": 0,
        "archer": 0,
        "spy": 1,
        "light": 0,
        "marcher": 0,
        "heavy": 0,
        "ram": 0,
        "catapult": 6,
        "knight": 0,
        "snob": 0,
        "militia": 0
      },
      "sent": false,
      "sentBy": null,
      "sentAt": null
    },
    {
      "id": "12151_9287_1778791179000",
      "originId": "12151",
      "targetId": "9287",
      "slowest": "catapult",
      "arrivalMs": 1778791179000,
      "catapultTarget": "14",
      "troops": {
        "spear": 0,
        "sword": 0,
        "axe": 0,
        "archer": 0,
        "spy": 1,
        "light": 0,
        "marcher": 0,
        "heavy": 0,
        "ram": 0,
        "catapult": 6,
        "knight": 0,
        "snob": 0,
        "militia": 0
      },
      "sent": false,
      "sentBy": null,
      "sentAt": null
    },
    {
      "id": "4765_3508_1778791339000",
      "originId": "4765",
      "targetId": "3508",
      "slowest": "catapult",
      "arrivalMs": 1778791339000,
      "catapultTarget": "14",
      "troops": {
        "spear": 0,
        "sword": 0,
        "axe": 0,
        "archer": 0,
        "spy": 1,
        "light": 0,
        "marcher": 0,
        "heavy": 0,
        "ram": 0,
        "catapult": 7,
        "knight": 0,
        "snob": 0,
        "militia": 0
      },
      "sent": false,
      "sentBy": null,
      "sentAt": null
    },
    {
      "id": "4765_11273_1778788232000",
      "originId": "4765",
      "targetId": "11273",
      "slowest": "catapult",
      "arrivalMs": 1778788232000,
      "catapultTarget": "14",
      "troops": {
        "spear": 0,
        "sword": 0,
        "axe": 0,
        "archer": 0,
        "spy": 1,
        "light": 0,
        "marcher": 0,
        "heavy": 0,
        "ram": 0,
        "catapult": 7,
        "knight": 0,
        "snob": 0,
        "militia": 0
      },
      "sent": false,
      "sentBy": null,
      "sentAt": null
    },
    {
      "id": "4765_13514_1778792061000",
      "originId": "4765",
      "targetId": "13514",
      "slowest": "catapult",
      "arrivalMs": 1778792061000,
      "catapultTarget": "14",
      "troops": {
        "spear": 0,
        "sword": 0,
        "axe": 0,
        "archer": 0,
        "spy": 1,
        "light": 0,
        "marcher": 0,
        "heavy": 0,
        "ram": 0,
        "catapult": 7,
        "knight": 0,
        "snob": 0,
        "militia": 0
      },
      "sent": false,
      "sentBy": null,
      "sentAt": null
    },
    {
      "id": "3547_2718_1778788165000",
      "originId": "3547",
      "targetId": "2718",
      "slowest": "catapult",
      "arrivalMs": 1778788165000,
      "catapultTarget": "14",
      "troops": {
        "spear": 0,
        "sword": 0,
        "axe": 0,
        "archer": 0,
        "spy": 1,
        "light": 0,
        "marcher": 0,
        "heavy": 0,
        "ram": 0,
        "catapult": 10,
        "knight": 0,
        "snob": 0,
        "militia": 0
      },
      "sent": false,
      "sentBy": null,
      "sentAt": null
    },
    {
      "id": "4765_8323_1778791593000",
      "originId": "4765",
      "targetId": "8323",
      "slowest": "catapult",
      "arrivalMs": 1778791593000,
      "catapultTarget": "14",
      "troops": {
        "spear": 0,
        "sword": 0,
        "axe": 0,
        "archer": 0,
        "spy": 1,
        "light": 0,
        "marcher": 0,
        "heavy": 0,
        "ram": 0,
        "catapult": 7,
        "knight": 0,
        "snob": 0,
        "militia": 0
      },
      "sent": false,
      "sentBy": null,
      "sentAt": null
    },
    {
      "id": "12151_11780_1778789018000",
      "originId": "12151",
      "targetId": "11780",
      "slowest": "catapult",
      "arrivalMs": 1778789018000,
      "catapultTarget": "14",
      "troops": {
        "spear": 0,
        "sword": 0,
        "axe": 0,
        "archer": 0,
        "spy": 1,
        "light": 0,
        "marcher": 0,
        "heavy": 0,
        "ram": 0,
        "catapult": 6,
        "knight": 0,
        "snob": 0,
        "militia": 0
      },
      "sent": false,
      "sentBy": null,
      "sentAt": null
    },
    {
      "id": "1999_6768_1778786083000",
      "originId": "1999",
      "targetId": "6768",
      "slowest": "catapult",
      "arrivalMs": 1778786083000,
      "catapultTarget": "14",
      "troops": {
        "spear": 0,
        "sword": 0,
        "axe": 0,
        "archer": 0,
        "spy": 1,
        "light": 0,
        "marcher": 0,
        "heavy": 0,
        "ram": 0,
        "catapult": 9,
        "knight": 0,
        "snob": 0,
        "militia": 0
      },
      "sent": false,
      "sentBy": null,
      "sentAt": null
    },
    {
      "id": "12151_9178_1778790009000",
      "originId": "12151",
      "targetId": "9178",
      "slowest": "catapult",
      "arrivalMs": 1778790009000,
      "catapultTarget": "14",
      "troops": {
        "spear": 0,
        "sword": 0,
        "axe": 0,
        "archer": 0,
        "spy": 1,
        "light": 0,
        "marcher": 0,
        "heavy": 0,
        "ram": 0,
        "catapult": 6,
        "knight": 0,
        "snob": 0,
        "militia": 0
      },
      "sent": false,
      "sentBy": null,
      "sentAt": null
    },
    {
      "id": "1999_7200_1778786167000",
      "originId": "1999",
      "targetId": "7200",
      "slowest": "catapult",
      "arrivalMs": 1778786167000,
      "catapultTarget": "14",
      "troops": {
        "spear": 0,
        "sword": 0,
        "axe": 0,
        "archer": 0,
        "spy": 1,
        "light": 0,
        "marcher": 0,
        "heavy": 0,
        "ram": 0,
        "catapult": 9,
        "knight": 0,
        "snob": 0,
        "militia": 0
      },
      "sent": false,
      "sentBy": null,
      "sentAt": null
    },
    {
      "id": "2507_8192_1778791496000",
      "originId": "2507",
      "targetId": "8192",
      "slowest": "catapult",
      "arrivalMs": 1778791496000,
      "catapultTarget": "14",
      "troops": {
        "spear": 0,
        "sword": 0,
        "axe": 0,
        "archer": 0,
        "spy": 1,
        "light": 0,
        "marcher": 0,
        "heavy": 0,
        "ram": 0,
        "catapult": 8,
        "knight": 0,
        "snob": 0,
        "militia": 0
      },
      "sent": false,
      "sentBy": null,
      "sentAt": null
    },
    {
      "id": "2507_7662_1778785354000",
      "originId": "2507",
      "targetId": "7662",
      "slowest": "catapult",
      "arrivalMs": 1778785354000,
      "catapultTarget": "14",
      "troops": {
        "spear": 0,
        "sword": 0,
        "axe": 0,
        "archer": 0,
        "spy": 1,
        "light": 0,
        "marcher": 0,
        "heavy": 0,
        "ram": 0,
        "catapult": 8,
        "knight": 0,
        "snob": 0,
        "militia": 0
      },
      "sent": false,
      "sentBy": null,
      "sentAt": null
    },
    {
      "id": "12151_7087_1778788804000",
      "originId": "12151",
      "targetId": "7087",
      "slowest": "catapult",
      "arrivalMs": 1778788804000,
      "catapultTarget": "14",
      "troops": {
        "spear": 0,
        "sword": 0,
        "axe": 0,
        "archer": 0,
        "spy": 1,
        "light": 0,
        "marcher": 0,
        "heavy": 0,
        "ram": 0,
        "catapult": 6,
        "knight": 0,
        "snob": 0,
        "militia": 0
      },
      "sent": false,
      "sentBy": null,
      "sentAt": null
    },
    {
      "id": "1999_3297_1778786698000",
      "originId": "1999",
      "targetId": "3297",
      "slowest": "catapult",
      "arrivalMs": 1778786698000,
      "catapultTarget": "14",
      "troops": {
        "spear": 0,
        "sword": 0,
        "axe": 0,
        "archer": 0,
        "spy": 1,
        "light": 0,
        "marcher": 0,
        "heavy": 0,
        "ram": 0,
        "catapult": 9,
        "knight": 0,
        "snob": 0,
        "militia": 0
      },
      "sent": false,
      "sentBy": null,
      "sentAt": null
    },
    {
      "id": "12151_5900_1778791819000",
      "originId": "12151",
      "targetId": "5900",
      "slowest": "catapult",
      "arrivalMs": 1778791819000,
      "catapultTarget": "14",
      "troops": {
        "spear": 0,
        "sword": 0,
        "axe": 0,
        "archer": 0,
        "spy": 1,
        "light": 0,
        "marcher": 0,
        "heavy": 0,
        "ram": 0,
        "catapult": 6,
        "knight": 0,
        "snob": 0,
        "militia": 0
      },
      "sent": false,
      "sentBy": null,
      "sentAt": null
    },
    {
      "id": "12151_8555_1778787565000",
      "originId": "12151",
      "targetId": "8555",
      "slowest": "catapult",
      "arrivalMs": 1778787565000,
      "catapultTarget": "14",
      "troops": {
        "spear": 0,
        "sword": 0,
        "axe": 0,
        "archer": 0,
        "spy": 1,
        "light": 0,
        "marcher": 0,
        "heavy": 0,
        "ram": 0,
        "catapult": 6,
        "knight": 0,
        "snob": 0,
        "militia": 0
      },
      "sent": false,
      "sentBy": null,
      "sentAt": null
    },
    {
      "id": "3547_5402_1778791202000",
      "originId": "3547",
      "targetId": "5402",
      "slowest": "catapult",
      "arrivalMs": 1778791202000,
      "catapultTarget": "14",
      "troops": {
        "spear": 0,
        "sword": 0,
        "axe": 0,
        "archer": 0,
        "spy": 1,
        "light": 0,
        "marcher": 0,
        "heavy": 0,
        "ram": 0,
        "catapult": 10,
        "knight": 0,
        "snob": 0,
        "militia": 0
      },
      "sent": false,
      "sentBy": null,
      "sentAt": null
    },
    {
      "id": "3547_6533_1778790330000",
      "originId": "3547",
      "targetId": "6533",
      "slowest": "catapult",
      "arrivalMs": 1778790330000,
      "catapultTarget": "14",
      "troops": {
        "spear": 0,
        "sword": 0,
        "axe": 0,
        "archer": 0,
        "spy": 1,
        "light": 0,
        "marcher": 0,
        "heavy": 0,
        "ram": 0,
        "catapult": 10,
        "knight": 0,
        "snob": 0,
        "militia": 0
      },
      "sent": false,
      "sentBy": null,
      "sentAt": null
    },
    {
      "id": "3547_5263_1778791259000",
      "originId": "3547",
      "targetId": "5263",
      "slowest": "catapult",
      "arrivalMs": 1778791259000,
      "catapultTarget": "14",
      "troops": {
        "spear": 0,
        "sword": 0,
        "axe": 0,
        "archer": 0,
        "spy": 1,
        "light": 0,
        "marcher": 0,
        "heavy": 0,
        "ram": 0,
        "catapult": 10,
        "knight": 0,
        "snob": 0,
        "militia": 0
      },
      "sent": false,
      "sentBy": null,
      "sentAt": null
    },
    {
      "id": "2507_5654_1778786067000",
      "originId": "2507",
      "targetId": "5654",
      "slowest": "catapult",
      "arrivalMs": 1778786067000,
      "catapultTarget": "14",
      "troops": {
        "spear": 0,
        "sword": 0,
        "axe": 0,
        "archer": 0,
        "spy": 1,
        "light": 0,
        "marcher": 0,
        "heavy": 0,
        "ram": 0,
        "catapult": 8,
        "knight": 0,
        "snob": 0,
        "militia": 0
      },
      "sent": false,
      "sentBy": null,
      "sentAt": null
    },
    {
      "id": "1999_9176_1778787113000",
      "originId": "1999",
      "targetId": "9176",
      "slowest": "catapult",
      "arrivalMs": 1778787113000,
      "catapultTarget": "14",
      "troops": {
        "spear": 0,
        "sword": 0,
        "axe": 0,
        "archer": 0,
        "spy": 1,
        "light": 0,
        "marcher": 0,
        "heavy": 0,
        "ram": 0,
        "catapult": 9,
        "knight": 0,
        "snob": 0,
        "militia": 0
      },
      "sent": false,
      "sentBy": null,
      "sentAt": null
    },
    {
      "id": "3547_5359_1778790074000",
      "originId": "3547",
      "targetId": "5359",
      "slowest": "catapult",
      "arrivalMs": 1778790074000,
      "catapultTarget": "14",
      "troops": {
        "spear": 0,
        "sword": 0,
        "axe": 0,
        "archer": 0,
        "spy": 1,
        "light": 0,
        "marcher": 0,
        "heavy": 0,
        "ram": 0,
        "catapult": 10,
        "knight": 0,
        "snob": 0,
        "militia": 0
      },
      "sent": false,
      "sentBy": null,
      "sentAt": null
    },
    {
      "id": "3547_10052_1778790955000",
      "originId": "3547",
      "targetId": "10052",
      "slowest": "catapult",
      "arrivalMs": 1778790955000,
      "catapultTarget": "14",
      "troops": {
        "spear": 0,
        "sword": 0,
        "axe": 0,
        "archer": 0,
        "spy": 1,
        "light": 0,
        "marcher": 0,
        "heavy": 0,
        "ram": 0,
        "catapult": 10,
        "knight": 0,
        "snob": 0,
        "militia": 0
      },
      "sent": false,
      "sentBy": null,
      "sentAt": null
    },
    {
      "id": "3547_7163_1778789715000",
      "originId": "3547",
      "targetId": "7163",
      "slowest": "catapult",
      "arrivalMs": 1778789715000,
      "catapultTarget": "14",
      "troops": {
        "spear": 0,
        "sword": 0,
        "axe": 0,
        "archer": 0,
        "spy": 1,
        "light": 0,
        "marcher": 0,
        "heavy": 0,
        "ram": 0,
        "catapult": 10,
        "knight": 0,
        "snob": 0,
        "militia": 0
      },
      "sent": false,
      "sentBy": null,
      "sentAt": null
    },
    {
      "id": "3547_8665_1778791766000",
      "originId": "3547",
      "targetId": "8665",
      "slowest": "catapult",
      "arrivalMs": 1778791766000,
      "catapultTarget": "14",
      "troops": {
        "spear": 0,
        "sword": 0,
        "axe": 0,
        "archer": 0,
        "spy": 1,
        "light": 0,
        "marcher": 0,
        "heavy": 0,
        "ram": 0,
        "catapult": 10,
        "knight": 0,
        "snob": 0,
        "militia": 0
      },
      "sent": false,
      "sentBy": null,
      "sentAt": null
    },
    {
      "id": "1999_6856_1778785427000",
      "originId": "1999",
      "targetId": "6856",
      "slowest": "catapult",
      "arrivalMs": 1778785427000,
      "catapultTarget": "14",
      "troops": {
        "spear": 0,
        "sword": 0,
        "axe": 0,
        "archer": 0,
        "spy": 1,
        "light": 0,
        "marcher": 0,
        "heavy": 0,
        "ram": 0,
        "catapult": 9,
        "knight": 0,
        "snob": 0,
        "militia": 0
      },
      "sent": false,
      "sentBy": null,
      "sentAt": null
    },
    {
      "id": "1999_9119_1778787397000",
      "originId": "1999",
      "targetId": "9119",
      "slowest": "catapult",
      "arrivalMs": 1778787397000,
      "catapultTarget": "14",
      "troops": {
        "spear": 0,
        "sword": 0,
        "axe": 0,
        "archer": 0,
        "spy": 1,
        "light": 0,
        "marcher": 0,
        "heavy": 0,
        "ram": 0,
        "catapult": 9,
        "knight": 0,
        "snob": 0,
        "militia": 0
      },
      "sent": false,
      "sentBy": null,
      "sentAt": null
    },
    {
      "id": "1999_2229_1778786157000",
      "originId": "1999",
      "targetId": "2229",
      "slowest": "catapult",
      "arrivalMs": 1778786157000,
      "catapultTarget": "14",
      "troops": {
        "spear": 0,
        "sword": 0,
        "axe": 0,
        "archer": 0,
        "spy": 1,
        "light": 0,
        "marcher": 0,
        "heavy": 0,
        "ram": 0,
        "catapult": 9,
        "knight": 0,
        "snob": 0,
        "militia": 0
      },
      "sent": false,
      "sentBy": null,
      "sentAt": null
    },
    {
      "id": "12151_10533_1778788397000",
      "originId": "12151",
      "targetId": "10533",
      "slowest": "catapult",
      "arrivalMs": 1778788397000,
      "catapultTarget": "14",
      "troops": {
        "spear": 0,
        "sword": 0,
        "axe": 0,
        "archer": 0,
        "spy": 1,
        "light": 0,
        "marcher": 0,
        "heavy": 0,
        "ram": 0,
        "catapult": 6,
        "knight": 0,
        "snob": 0,
        "militia": 0
      },
      "sent": false,
      "sentBy": null,
      "sentAt": null
    },
    {
      "id": "1999_5751_1778785202000",
      "originId": "1999",
      "targetId": "5751",
      "slowest": "catapult",
      "arrivalMs": 1778785202000,
      "catapultTarget": "14",
      "troops": {
        "spear": 0,
        "sword": 0,
        "axe": 0,
        "archer": 0,
        "spy": 1,
        "light": 0,
        "marcher": 0,
        "heavy": 0,
        "ram": 0,
        "catapult": 9,
        "knight": 0,
        "snob": 0,
        "militia": 0
      },
      "sent": false,
      "sentBy": null,
      "sentAt": null
    }
  ]
}